go_vendor_tools/__init__.py
go_vendor_tools/_zstarfile_extra.py
go_vendor_tools/archive.py
go_vendor_tools/exceptions.py
go_vendor_tools/gomod.py
go_vendor_tools/hashing.py
go_vendor_tools/licensing.py
go_vendor_tools/py.typed
go_vendor_tools/specfile.py
go_vendor_tools/cli/__init__.py
go_vendor_tools/cli/go_vendor_archive.py
go_vendor_tools/cli/go_vendor_license.py
go_vendor_tools/cli/gocheck2.py
go_vendor_tools/cli/utils.py
go_vendor_tools/config/__init__.py
go_vendor_tools/config/archive.py
go_vendor_tools/config/base.py
go_vendor_tools/config/general.py
go_vendor_tools/config/licenses.py
go_vendor_tools/config/utils.py
go_vendor_tools/license_detection/__init__.py
go_vendor_tools/license_detection/askalono.py
go_vendor_tools/license_detection/base.py
go_vendor_tools/license_detection/load.py
go_vendor_tools/license_detection/scancode.py
go_vendor_tools/license_detection/search.py
go_vendor_tools/license_detection/trivy.py
go_vendor_tools-0.9.0.dist-info/METADATA
go_vendor_tools-0.9.0.dist-info/WHEEL
go_vendor_tools-0.9.0.dist-info/entry_points.txt
go_vendor_tools-0.9.0.dist-info/licenses/LICENSES/BSD-3-Clause.txt
go_vendor_tools-0.9.0.dist-info/licenses/LICENSES/LicenseRef-Not-Copyrightable.txt
go_vendor_tools-0.9.0.dist-info/licenses/LICENSES/MIT.txt
go_vendor_tools-0.9.0.dist-info/RECORD
