Metadata-Version: 2.4
Name: go-vendor-tools
Version: 0.9.0
Summary: Tools for handling Go library vendoring in Fedora
Project-URL: Homepage, https://fedora.gitlab.io/sigs/go/go-vendor-tools/
Project-URL: Source, https://gitlab.com/fedora/sigs/go/go-vendor-tools
Project-URL: Issue Tracker, https://gitlab.com/fedora/sigs/go/go-vendor-tools/-/issues
Project-URL: Changelog, https://fedora.gitlab.io/sigs/go/go-vendor-tools/news/
Author-email: Maxwell G <maxwell@gtmx.me>
Maintainer-email: Maxwell G <maxwell@gtmx.me>, Fedora Go SIG <golang@lists.fedoraproject.org>
License-Expression: MIT AND BSD-3-Clause
License-File: LICENSES/BSD-3-Clause.txt
License-File: LICENSES/LicenseRef-Not-Copyrightable.txt
License-File: LICENSES/MIT.txt
Classifier: Development Status :: 3 - Alpha
Classifier: License :: OSI Approved :: MIT License
Classifier: Programming Language :: Python :: 3
Classifier: Programming Language :: Python :: 3 :: Only
Classifier: Programming Language :: Python :: 3.9
Classifier: Programming Language :: Python :: 3.10
Classifier: Programming Language :: Python :: 3.11
Classifier: Programming Language :: Python :: 3.12
Classifier: Typing :: Typed
Requires-Python: >=3.9
Requires-Dist: license-expression
Requires-Dist: tomli; python_version < '3.11'
Provides-Extra: all
Requires-Dist: argcomplete; extra == 'all'
Requires-Dist: specfile; extra == 'all'
Requires-Dist: tomlkit; extra == 'all'
Requires-Dist: zstarfile; extra == 'all'
Provides-Extra: codeqa
Requires-Dist: pymarkdownlnt; extra == 'codeqa'
Requires-Dist: reuse; extra == 'codeqa'
Requires-Dist: ruff>=0.3.0; extra == 'codeqa'
Requires-Dist: shellcheck-py; extra == 'codeqa'
Provides-Extra: dev
Requires-Dist: argcomplete; extra == 'dev'
Requires-Dist: black; extra == 'dev'
Requires-Dist: isort; extra == 'dev'
Requires-Dist: mkdocs-gen-files; extra == 'dev'
Requires-Dist: mypy; extra == 'dev'
Requires-Dist: nox; extra == 'dev'
Requires-Dist: pymarkdownlnt; extra == 'dev'
Requires-Dist: pytest; extra == 'dev'
Requires-Dist: pytest-mock; extra == 'dev'
Requires-Dist: releaserr; extra == 'dev'
Requires-Dist: reuse; extra == 'dev'
Requires-Dist: ruff>=0.3.0; extra == 'dev'
Requires-Dist: shellcheck-py; extra == 'dev'
Requires-Dist: specfile; extra == 'dev'
Requires-Dist: tomlkit; extra == 'dev'
Requires-Dist: typing-extensions; extra == 'dev'
Requires-Dist: zstarfile; extra == 'dev'
Provides-Extra: formatters
Requires-Dist: black; extra == 'formatters'
Requires-Dist: isort; extra == 'formatters'
Provides-Extra: scancode
Requires-Dist: scancode-toolkit; extra == 'scancode'
Provides-Extra: specfile
Requires-Dist: specfile; extra == 'specfile'
Provides-Extra: test
Requires-Dist: argcomplete; extra == 'test'
Requires-Dist: pytest; extra == 'test'
Requires-Dist: pytest-mock; extra == 'test'
Requires-Dist: specfile; extra == 'test'
Requires-Dist: tomlkit; extra == 'test'
Requires-Dist: zstarfile; extra == 'test'
Provides-Extra: typing
Requires-Dist: argcomplete; extra == 'typing'
Requires-Dist: mkdocs-gen-files; extra == 'typing'
Requires-Dist: mypy; extra == 'typing'
Requires-Dist: nox; extra == 'typing'
Requires-Dist: pytest; extra == 'typing'
Requires-Dist: pytest-mock; extra == 'typing'
Requires-Dist: releaserr; extra == 'typing'
Requires-Dist: specfile; extra == 'typing'
Requires-Dist: tomlkit; extra == 'typing'
Requires-Dist: typing-extensions; extra == 'typing'
Requires-Dist: zstarfile; extra == 'typing'
